{"columns" : {
    "fields": [
      {
        "Key": "id_sess",
        "DisplayName": "Session Id",
        "IsColumn": false,
        "Sortable" : false,
        "Filterable" : false,
        "Exportable" : false,
        "DefaultColumn": false,
        "DataType": "Numeric",
        "IsCurrency": false
      },
      {
        "Key": "currency",
        "DisplayName": "Currency",
        "IsColumn": false,
        "Sortable" : false,
        "Filterable" : false,
        "Exportable" : false,
        "DefaultColumn": false,
        "DataType": "String",
        "IsCurrency": false
      },
      {
        "Key": "unadjustedamount",
        "DisplayName": "Unadjusted Amount",
        "IsColumn": false,
        "Sortable" : false,
        "Filterable" : false,
        "Exportable" : false,
        "DefaultColumn": false,
        "DataType": "Numeric",
        "IsCurrency": true,
        "CurrencySymbol": "currency"
      },
      {
        "Key": "unadjustedamountwithtax",
        "DisplayName": "Unadjusted Amount with Tax",
        "IsColumn": false,
        "Sortable" : false,
        "Filterable" : false,
        "Exportable" : false,
        "DefaultColumn": false,
        "DataType": "Numeric",
        "IsCurrency": true,
        "CurrencySymbol": "currency"
      },
      {
        "Key": "totalfederaltax",
        "DisplayName": "Total Federal Tax",
        "IsColumn": false,
        "Sortable" : false,
        "Filterable" : false,
        "Exportable" : false,
        "DefaultColumn": false,
        "DataType": "Numeric",
        "IsCurrency": true,
        "CurrencySymbol": "currency"
      },
      {
        "Key": "totalstatetax",
        "DisplayName": "Total State Tax",
        "IsColumn": false,
        "Sortable" : false,
        "Filterable" : false,
        "Exportable" : false,
        "DefaultColumn": false,
        "DataType": "Numeric",
        "IsCurrency": true,
        "CurrencySymbol": "currency"
      },
      {
        "Key": "totalcountytax",
        "DisplayName": "Total Country Tax",
        "IsColumn": false,
        "Sortable" : false,
        "Filterable" : false,
        "Exportable" : false,
        "DefaultColumn": false,
        "DataType": "Numeric",
        "IsCurrency": true,
        "CurrencySymbol": "currency"
      },
      {
        "Key": "totallocaltax",
        "DisplayName": "Total Local Tax",
        "IsColumn": false,
        "Sortable" : false,
        "Filterable" : false,
        "Exportable" : false,
        "DefaultColumn": false,
        "DataType": "Numeric",
        "IsCurrency": true,
        "CurrencySymbol": "currency"
      },
      {
        "Key": "totalothertax",
        "DisplayName": "Total Other Tax",
        "IsColumn": false,
        "Sortable" : false,
        "Filterable" : false,
        "Exportable" : false,
        "DefaultColumn": false,
        "DataType": "Numeric",
        "IsCurrency": true,
        "CurrencySymbol": "currency"
      },
      {
        "Key": "postbillfedtaxadjamt",
        "DisplayName": "Postbill Fed Tax Adjust Amount",
        "IsColumn": false,
        "Sortable" : false,
        "Filterable" : false,
        "Exportable" : false,
        "DefaultColumn": false,
        "DataType": "Numeric",
        "IsCurrency": true,
        "CurrencySymbol": "currency"
      },
      {
        "Key": "postbillstatetaxadjamt",
        "DisplayName": "Postbill Federal Tax Adjust Amount",
        "IsColumn": false,
        "Sortable" : false,
        "Filterable" : false,
        "Exportable" : false,
        "DefaultColumn": false,
        "DataType": "Numeric",
        "IsCurrency": true,
        "CurrencySymbol": "currency"
      },
      {
        "Key": "postbillcntytaxadjamt",
        "DisplayName": "Postbill Country Tax Adjust Amount",
        "IsColumn": false,
        "Sortable" : false,
        "Filterable" : false,
        "Exportable" : false,
        "DefaultColumn": false,
        "DataType": "Numeric",
        "IsCurrency": true,
        "CurrencySymbol": "currency"
      },
      {
        "Key": "postbilllocaltaxadjamt",
        "DisplayName": "Postbill Local Tax Adjust Amount",
        "IsColumn": false,
        "Sortable" : false,
        "Filterable" : false,
        "Exportable" : false,
        "DefaultColumn": false,
        "DataType": "Numeric",
        "IsCurrency": true,
        "CurrencySymbol": "currency"
      },
      {
        "Key": "postbillothertaxadjamt",
        "DisplayName": "Postbill Other Tax Adjust Amount",
        "IsColumn": false,
        "Sortable" : false,
        "Filterable" : false,
        "Exportable" : false,
        "DefaultColumn": false,
        "DataType": "Numeric",
        "IsCurrency": true,
        "CurrencySymbol": "currency"
      },
      {
        "Key": "prebillfedtaxadjamt",
        "DisplayName": "Prebill Federal Tax Adjust Amount",
        "IsColumn": false,
        "Sortable" : false,
        "Filterable" : false,
        "Exportable" : false,
        "DefaultColumn": false,
        "DataType": "Numeric",
        "IsCurrency": true,
        "CurrencySymbol": "currency"
      },
      {
        "Key": "prebillstatetaxadjamt",
        "DisplayName": "Prebill State Tax Adjust Amount",
        "IsColumn": false,
        "Sortable" : false,
        "Filterable" : false,
        "Exportable" : false,
        "DefaultColumn": false,
        "DataType": "Numeric",
        "IsCurrency": true,
        "CurrencySymbol": "currency"
      },
      {
        "Key": "prebillcntytaxadjamt",
        "DisplayName": "prebillcntytaxadjamt",
        "IsColumn": false,
        "Sortable" : false,
        "Filterable" : false,
        "Exportable" : false,
        "DefaultColumn": false,
        "DataType": "Numeric",
        "IsCurrency": true,
        "CurrencySymbol": "currency"
      },
      {
        "Key": "prebilllocaltaxadjamt",
        "DisplayName": "Prebill Local Tax Adjust Amount",
        "IsColumn": false,
        "Sortable" : false,
        "Filterable" : false,
        "Exportable" : false,
        "DefaultColumn": false,
        "DataType": "Numeric",
        "IsCurrency": true,
        "CurrencySymbol": "currency"
      },
      {
        "Key": "prebillothertaxadjamt",
        "DisplayName": "Prebill Other Tax Adjust Amount",
        "IsColumn": false,
        "Sortable" : false,
        "Filterable" : false,
        "Exportable" : false,
        "DefaultColumn": false,
        "DataType": "Numeric",
        "IsCurrency": true,
        "CurrencySymbol": "currency"
      },
      {
        "Key": "adjustmentamount",
        "DisplayName": "Adjustment Amount",
        "IsColumn": true,
        "Sortable" : true,
        "Filterable" : true,
        "Exportable" : true,
        "DefaultColumn": true,
        "DataType": "Numeric",
        "IsCurrency": true,
        "CurrencySymbol": "currency"
      },
      {
        "Key": "adjustedamount",
        "DisplayName": "Adjusted Amount",
        "IsColumn": false,
        "Sortable" : false,
        "Filterable" : false,
        "Exportable" : false,
        "DefaultColumn": false,
        "DataType": "Numeric",
        "IsCurrency": true,
        "CurrencySymbol": "currency"
      },
      {
        "Key": "adjustmentamountwithtax",
        "DisplayName": "Adjustment Amount With Tax",
        "IsColumn": false,
        "Sortable" : false,
        "Filterable" : false,
        "Exportable" : false,
        "DefaultColumn": false,
        "DataType": "Numeric",
        "IsCurrency": true,
        "CurrencySymbol": "currency"
      },
      {
        "Key": "adjustedamountwithtax",
        "DisplayName": "Adjusted Amount With Tax",
        "IsColumn": false,
        "Sortable" : false,
        "Filterable" : false,
        "Exportable" : false,
        "DefaultColumn": false,
        "DataType": "Numeric",
        "IsCurrency": true,
        "CurrencySymbol": "currency"
      },
      {
        "Key": "adjustmenttemplatedisplayname",
        "DisplayName": "Adjustment Template Display Name",
        "IsColumn": false,
        "Sortable" : false,
        "Filterable" : false,
        "Exportable" : false,
        "DefaultColumn": false,
        "DataType": "String",
        "IsCurrency": false
      },
      {
        "Key": "adjustmentinstancedisplayname",
        "DisplayName": "Adjustment Instanced Display Name",
        "IsColumn": true,
        "Sortable" : true,
        "Filterable" : true,
        "Exportable" : true,
        "DefaultColumn": true,
        "DataType": "String",
        "IsCurrency": false
      },
      {
        "Key": "description",
        "DisplayName": "Description",
        "IsColumn": true,
        "Sortable" : true,
        "Filterable" : true,
        "Exportable" : true,
        "DefaultColumn": true,
        "DataType": "String",
        "IsCurrency": false
      },
      {
        "Key": "reasoncode",
        "DisplayName": "Reason Code",
        "IsColumn": false,
        "Sortable" : false,
        "Filterable" : false,
        "Exportable" : false,
        "DefaultColumn": false,
        "DataType": "Numeric",
        "IsCurrency": false
      },
      {
        "Key": "reasoncodename",
        "DisplayName": "Reason",
        "IsColumn": false,
        "Sortable" : false,
        "Filterable" : false,
        "Exportable" : false,
        "DefaultColumn": false,
        "DataType": "String",
        "IsCurrency": false
      },
      {
        "Key": "reasoncodedescription",
        "DisplayName": "Reason Code Description",
        "IsColumn": false,
        "Sortable" : false,
        "Filterable" : false,
        "Exportable" : false,
        "DefaultColumn": false,
        "DataType": "String",
        "IsCurrency": false
      },
      {
        "Key": "reasoncodedisplayname",
        "DisplayName": "Reason Code Display Name",
        "IsColumn": false,
        "Sortable" : false,
        "Filterable" : false,
        "Exportable" : false,
        "DefaultColumn": false,
        "DataType": "String",
        "IsCurrency": false
      },
      {
        "Key": "id_usage_interval",
        "DisplayName": "Usage Interval Id",
        "IsColumn": false,
        "Sortable" : false,
        "Filterable" : false,
        "Exportable" : false,
        "DefaultColumn": false,
        "DataType": "Numeric",
        "IsCurrency": false
      },
      {
        "Key": "id_acc",
        "DisplayName": "Account Id",
        "IsColumn": false,
        "Sortable" : false,
        "Filterable" : false,
        "Exportable" : false,
        "DefaultColumn": false,
        "DataType": "Numeric",
        "IsCurrency": false
      },
      {
        "Key": "n_adjustmenttype",
        "DisplayName": "Adjustment Type",
        "IsColumn": false,
        "Sortable" : false,
        "Filterable" : false,
        "Exportable" : false,
        "DefaultColumn": false,
        "DataType": "String",
        "IsCurrency": false
      },
      {
        "Key": "dt_session",
        "DisplayName": "Session Date",
        "IsColumn": false,
        "Sortable" : false,
        "Filterable" : false,
        "Exportable" : false,
        "DefaultColumn": false,
        "DataType": "Date",
        "IsCurrency": false
      }
    ]}
}
